pbi_core/__init__.py
pbi_core/__main__.py
pbi_core/logging.py
pbi_core/main.py
pbi_core/attrs/__init__.py
pbi_core/attrs/attrs.py
pbi_core/attrs/cattrs.py
pbi_core/attrs/extra.py
pbi_core/attrs/extra_json.py
pbi_core/lineage/__init__.py
pbi_core/lineage/main.py
pbi_core/misc/__init__.py
pbi_core/misc/remove_workspaces.py
pbi_core/misc/internationalization/__init__.py
pbi_core/misc/internationalization/get_static_elements.py
pbi_core/misc/internationalization/main.py
pbi_core/misc/internationalization/set_static_elements.py
pbi_core/misc/internationalization/text_elements.py
pbi_core/report/__init__.py
pbi_core/report/base/__init__.py
pbi_core/report/base/main.py
pbi_core/report/base/ssas.py
pbi_core/report/base/static_files.py
pbi_core/report/local/__init__.py
pbi_core/report/local/main.py
pbi_core/report/local/ssas.py
pbi_core/report/local/static_files.py
pbi_core/ssas/__init__.py
pbi_core/ssas/model_tables/__init__.py
pbi_core/ssas/model_tables/_group.py
pbi_core/ssas/model_tables/alternate_of/__init__.py
pbi_core/ssas/model_tables/alternate_of/alternate_of.py
pbi_core/ssas/model_tables/annotation/__init__.py
pbi_core/ssas/model_tables/annotation/annotation.py
pbi_core/ssas/model_tables/annotation/local.py
pbi_core/ssas/model_tables/attribute_hierarchy/__init__.py
pbi_core/ssas/model_tables/attribute_hierarchy/attribute_hierarchy.py
pbi_core/ssas/model_tables/base/__init__.py
pbi_core/ssas/model_tables/base/base_ssas_table.py
pbi_core/ssas/model_tables/base/enums.py
pbi_core/ssas/model_tables/base/helpers.py
pbi_core/ssas/model_tables/base/lineage.py
pbi_core/ssas/model_tables/base/ssas.py
pbi_core/ssas/model_tables/base/ssas_tables.py
pbi_core/ssas/model_tables/base/tabular.py
pbi_core/ssas/model_tables/calc_dependency/__init__.py
pbi_core/ssas/model_tables/calc_dependency/calc_dependency.py
pbi_core/ssas/model_tables/calculation_group/__init__.py
pbi_core/ssas/model_tables/calculation_group/calculation_group.py
pbi_core-0.7.0.dist-info/METADATA
pbi_core-0.7.0.dist-info/WHEEL
pbi_core-0.7.0.dist-info/licenses/LICENSE
pbi_core-0.7.0.dist-info/RECORD
