Metadata-Version: 2.4
Name: pbi_core
Version: 0.7.0
Summary: Accessing PBIX files programmatically
Project-URL: Homepage, https://github.com/douglassimonsen/pbi_core
Project-URL: Documentation, https://douglassimonsen.github.io/pbi_core/
License-File: LICENSE
Requires-Python: >=3.11.0
Requires-Dist: attrs>=25.3.0
Requires-Dist: backoff>=2.2.1
Requires-Dist: beautifulsoup4>=4.12.3
Requires-Dist: cattrs>=25.2.0
Requires-Dist: gitpython>=3.1
Requires-Dist: inquirer>=3.4.0
Requires-Dist: jinja2>=3.1.6
Requires-Dist: jsondiff>=2.2.1
Requires-Dist: lxml>=5.3.0
Requires-Dist: pbi-mermaid>=0.4.0
Requires-Dist: pbi-parsers>=0.9.5
Requires-Dist: pbi-prototype-query-translation>=1.1.6
Requires-Dist: pbi-pyadomd>=1.4.2
Requires-Dist: psutil>=6.0.0
Requires-Dist: pytest>=8.3.2
Requires-Dist: python-dotenv>=1.0.1
Requires-Dist: pythonnet>=3.0.5
Requires-Dist: pywin32>=311; platform_system == 'Windows'
Requires-Dist: semver>=3.0.4
Requires-Dist: structlog>=24.4.0
Provides-Extra: dev
Requires-Dist: build>=1.2.2; extra == 'dev'
Requires-Dist: click>=8.1.8; extra == 'dev'
Requires-Dist: inquirer>=3.4.0; extra == 'dev'
Requires-Dist: mypy>=1.11.2; extra == 'dev'
Requires-Dist: pre-commit>=3.8.0; extra == 'dev'
Requires-Dist: requests>=2.32.4; extra == 'dev'
Requires-Dist: ruff>=0.12.8; extra == 'dev'
Provides-Extra: docs
Requires-Dist: mkdocs-glightbox>=0.5.1; extra == 'docs'
Requires-Dist: mkdocs-material>=9.6.16; extra == 'docs'
Requires-Dist: mkdocs>=1.6.1; extra == 'docs'
Requires-Dist: mkdocstrings-python>=0.30.0; extra == 'docs'
Provides-Extra: internationalization
Requires-Dist: langcodes>=3.4.1; extra == 'internationalization'
Requires-Dist: openpyxl>=3.1.5; extra == 'internationalization'
